pyrql/__init__.py
pyrql/exceptions.py
pyrql/parser.py
pyrql/query.py
pyrql/unparser.py
pyrql-0.7.10.dist-info/METADATA
pyrql-0.7.10.dist-info/WHEEL
pyrql-0.7.10.dist-info/licenses/LICENSE
pyrql-0.7.10.dist-info/RECORD
