Metadata-Version: 2.4
Name: pyrql
Version: 0.7.10
Summary: RQL parsing
Project-URL: Repository, https://github.com/pjwerneck/pyrql
Project-URL: Bug Tracker, https://github.com/pjwerneck/pyrql/issues
Author-email: Pedro Werneck <pjwerneck@gmail.com>
License-Expression: MIT
License-File: LICENSE
Classifier: License :: OSI Approved :: MIT License
Classifier: Operating System :: OS Independent
Classifier: Programming Language :: Python :: 3
Classifier: Programming Language :: Python :: 3.8
Classifier: Programming Language :: Python :: 3.9
Classifier: Programming Language :: Python :: 3.10
Classifier: Programming Language :: Python :: 3.11
Classifier: Programming Language :: Python :: 3.12
Requires-Python: ~=3.8
Requires-Dist: pyparsing~=3.1
Requires-Dist: python-dateutil~=2.8
